scMGCA/graph_function.py
scMGCA/layers.py
scMGCA/losses.py
scMGCA/preprocess.py
scMGCA/scmgca.py
scMGCA/scmgca_para.py
scMGCA/utils.py
scMGCA-1.0.7.dist-info/LICENSE
scMGCA-1.0.7.dist-info/METADATA
scMGCA-1.0.7.dist-info/WHEEL
scMGCA-1.0.7.dist-info/top_level.txt
scMGCA-1.0.7.dist-info/RECORD
