Metadata-Version: 2.1
Name: scMGCA
Version: 1.0.7
Summary: Topological Identification and Interpretation for High-throughput Single-cell Gene Regulation Elucidation across Multiple Platforms using scMGCA
Home-page: https://github.com/Philyzh8/scMGCA
Author: Zhuohan Yu
Author-email: zhuohan20@mails.jlu.edu.cn
License: MIT
Platform: UNKNOWN
Classifier: Operating System :: OS Independent
Classifier: Topic :: Scientific/Engineering :: Artificial Intelligence
Classifier: Programming Language :: Python :: 3.6
